LICENSE
README.md
setup.py
EventEmitterPy/__init__.py
EventEmitterPy/emitter.py
EventEmitterPy.egg-info/PKG-INFO
EventEmitterPy.egg-info/SOURCES.txt
EventEmitterPy.egg-info/dependency_links.txt
EventEmitterPy.egg-info/top_level.txt