Metadata-Version: 2.1
Name: EventEmitterPy
Version: 0.2.0
Summary: A super fast, memory effcient events system for Python
Home-page: UNKNOWN
Author: Ahmed Rakan
Author-email: ar.aldhafeeri11@gmail.com
License: UNKNOWN
Platform: UNKNOWN
License-File: LICENSE
